{
  "uid" : "4c37cfc9fb3a24f3",
  "name" : "TestLogin.test_login[password_success]",
  "title" : "Test login [password_success]",
  "time" : {
    "start" : 1560250679967,
    "stop" : 1560250680977,
    "duration" : 1010
  },
  "summary" : {
    "attachments" : 13,
    "steps" : 3
  },
  "failure" : null,
  "description" : {
    "value" : "\n        登录用例\n        :param case_data: 测试用例\n        :return:\n        ",
    "type" : "TEXT"
  },
  "severity" : "NORMAL",
  "status" : "PASSED",
  "testId" : null,
  "suite" : {
    "uid" : "d10d71a6c1be128",
    "name" : "test_login",
    "title" : "Test login"
  },
  "steps" : [ {
    "name" : "保存cookie信息",
    "title" : "保存cookie信息",
    "time" : {
      "start" : 1560250679974,
      "stop" : 1560250680454,
      "duration" : 480
    },
    "summary" : {
      "attachments" : 4,
      "steps" : 0
    },
    "status" : "PASSED",
    "attachments" : [ {
      "title" : "请求接口：",
      "source" : "67c9666e-1a62-4330-9c41-251626c18a41-attachment.txt",
      "type" : "text/plain",
      "size" : 14,
      "uid" : "d727ac5d05a22ef7"
    }, {
      "title" : "请求地址",
      "source" : "dcadfc87-ae13-44c5-91e2-82c902c9a9d2-attachment.txt",
      "type" : "text/plain",
      "size" : 46,
      "uid" : "3cc8a4123352bc34"
    }, {
      "title" : "请求头",
      "source" : "b94e99a9-487b-4fe4-b32c-d92c1d5c31ae-attachment.txt",
      "type" : "text/plain",
      "size" : 38,
      "uid" : "d0aa179dd64a0668"
    }, {
      "title" : "请求参数",
      "source" : "03ce0008-622d-46eb-8b6f-2b58ab9f2f6f-attachment.txt",
      "type" : "text/plain",
      "size" : 69,
      "uid" : "aef7c5f014e33fbc"
    } ],
    "steps" : [ ]
  }, {
    "name" : "POST请求接口",
    "title" : "POST请求接口",
    "time" : {
      "start" : 1560250680454,
      "stop" : 1560250680454,
      "duration" : 0
    },
    "summary" : {
      "attachments" : 4,
      "steps" : 0
    },
    "status" : "PASSED",
    "attachments" : [ {
      "title" : "请求接口：",
      "source" : "587f0f5a-6b5f-40b0-b29e-75bf230485c7-attachment.txt",
      "type" : "text/plain",
      "size" : 14,
      "uid" : "72f43be272f86a90"
    }, {
      "title" : "请求地址",
      "source" : "03daebc3-6c4e-448e-b692-1bc3905b0b57-attachment.txt",
      "type" : "text/plain",
      "size" : 46,
      "uid" : "196d60059c34a29c"
    }, {
      "title" : "请求头",
      "source" : "04c7b9be-9f83-44e7-a4dc-56fc2d7d9441-attachment.txt",
      "type" : "text/plain",
      "size" : 38,
      "uid" : "b4387489eca6efff"
    }, {
      "title" : "请求参数",
      "source" : "e0fdf8c3-5598-457a-9f21-769de237df65-attachment.txt",
      "type" : "text/plain",
      "size" : 69,
      "uid" : "9f76bcfe21f60b57"
    } ],
    "steps" : [ ]
  }, {
    "name" : "完全校验",
    "title" : "完全校验",
    "time" : {
      "start" : 1560250680976,
      "stop" : 1560250680976,
      "duration" : 0
    },
    "summary" : {
      "attachments" : 4,
      "steps" : 0
    },
    "status" : "PASSED",
    "attachments" : [ {
      "title" : "期望code",
      "source" : "11396585-1f30-4ff4-8036-48af64fade73-attachment.txt",
      "type" : "text/plain",
      "size" : 3,
      "uid" : "67f7690dac8387d2"
    }, {
      "title" : "期望data",
      "source" : "f1c7055d-ee2d-480f-b6e6-fc27a7449920-attachment.txt",
      "type" : "text/plain",
      "size" : 980,
      "uid" : "794da3f6ce7f0f7a"
    }, {
      "title" : "实际code",
      "source" : "aef38611-ee59-4fd3-a67f-7694d9048e56-attachment.txt",
      "type" : "text/plain",
      "size" : 3,
      "uid" : "3c4e58ea46116d9e"
    }, {
      "title" : "实际data",
      "source" : "2d0a9f3b-d71c-43d4-b68d-d4dca9a6bf7b-attachment.txt",
      "type" : "text/plain",
      "size" : 980,
      "uid" : "44b5d04f429dc975"
    } ],
    "steps" : [ ]
  } ],
  "attachments" : [ {
    "title" : "Captured log call",
    "source" : "36fae956-44ac-4e06-b5c9-ee07b05726a6-attachment.txt",
    "type" : "text/plain",
    "size" : 3106,
    "uid" : "e4ce8a0638e5de94"
  } ],
  "issues" : [ ],
  "labels" : [ {
    "name" : "story",
    "value" : "login"
  }, {
    "name" : "feature",
    "value" : "login"
  }, {
    "name" : "thread",
    "value" : "40462-MainThread"
  }, {
    "name" : "suite-name",
    "value" : "test_login"
  }, {
    "name" : "framework",
    "value" : "pytest"
  }, {
    "name" : "suite-title",
    "value" : null
  }, {
    "name" : "severity",
    "value" : "normal"
  }, {
    "name" : "host",
    "value" : "xiaoxideMacBook-Pro.local"
  }, {
    "name" : "language",
    "value" : "cpython3"
  } ],
  "parameters" : [ ]
}