{
  "uid" : "8b54cbd256f5a768",
  "name" : "TestLogin.test_login[password_success]",
  "title" : "Test login [password_success]",
  "time" : {
    "start" : 1560328748769,
    "stop" : 1560328749982,
    "duration" : 1213
  },
  "summary" : {
    "attachments" : 13,
    "steps" : 3
  },
  "failure" : null,
  "description" : {
    "value" : "\n        登录用例\n        :param case_data: 测试用例\n        :return:\n        ",
    "type" : "TEXT"
  },
  "severity" : "NORMAL",
  "status" : "PASSED",
  "testId" : null,
  "suite" : {
    "uid" : "98d9726b2654b6fa",
    "name" : "test_a_login",
    "title" : "Test a login"
  },
  "steps" : [ {
    "name" : "保存cookie信息",
    "title" : "保存cookie信息",
    "time" : {
      "start" : 1560328748779,
      "stop" : 1560328749378,
      "duration" : 599
    },
    "summary" : {
      "attachments" : 4,
      "steps" : 0
    },
    "status" : "PASSED",
    "attachments" : [ {
      "title" : "请求接口：",
      "source" : "a7dc2e9e-a3d3-47ea-bfcc-b4c749c45fc6-attachment.txt",
      "type" : "text/plain",
      "size" : 14,
      "uid" : "b1fec99e2812441"
    }, {
      "title" : "请求地址",
      "source" : "79b99661-580a-4e38-b342-3d2cd10fef35-attachment.txt",
      "type" : "text/plain",
      "size" : 46,
      "uid" : "d1304843279ba510"
    }, {
      "title" : "请求头",
      "source" : "6ae70f2b-74b3-4f5f-bba2-74c194c478a2-attachment.txt",
      "type" : "text/plain",
      "size" : 38,
      "uid" : "4f7422f632878656"
    }, {
      "title" : "请求参数",
      "source" : "62b136ca-5973-4ea8-a298-87695383df4c-attachment.txt",
      "type" : "text/plain",
      "size" : 69,
      "uid" : "30472c219b470126"
    } ],
    "steps" : [ ]
  }, {
    "name" : "POST请求接口",
    "title" : "POST请求接口",
    "time" : {
      "start" : 1560328749379,
      "stop" : 1560328749379,
      "duration" : 0
    },
    "summary" : {
      "attachments" : 4,
      "steps" : 0
    },
    "status" : "PASSED",
    "attachments" : [ {
      "title" : "请求接口：",
      "source" : "b570a15f-54ba-41fd-8cac-9fc8be09b6c9-attachment.txt",
      "type" : "text/plain",
      "size" : 14,
      "uid" : "ae18cc4d2e9e58e3"
    }, {
      "title" : "请求地址",
      "source" : "dd637895-15f8-49d9-ae0e-f49b72c3fd2d-attachment.txt",
      "type" : "text/plain",
      "size" : 46,
      "uid" : "1762135574f02719"
    }, {
      "title" : "请求头",
      "source" : "03e9fa86-0c46-4aa7-b4e1-63e39f84e18b-attachment.txt",
      "type" : "text/plain",
      "size" : 38,
      "uid" : "d5951da03309dfd0"
    }, {
      "title" : "请求参数",
      "source" : "6ecb99e8-e944-470d-bee6-f533217d818e-attachment.txt",
      "type" : "text/plain",
      "size" : 69,
      "uid" : "27d7f4693e2cd3c1"
    } ],
    "steps" : [ ]
  }, {
    "name" : "完全校验",
    "title" : "完全校验",
    "time" : {
      "start" : 1560328749981,
      "stop" : 1560328749981,
      "duration" : 0
    },
    "summary" : {
      "attachments" : 4,
      "steps" : 0
    },
    "status" : "PASSED",
    "attachments" : [ {
      "title" : "期望code",
      "source" : "2da66637-3241-43c3-972b-9da99dd8e246-attachment.txt",
      "type" : "text/plain",
      "size" : 3,
      "uid" : "30abe452c884fed2"
    }, {
      "title" : "期望data",
      "source" : "cbbac4bb-36f3-4917-b0ee-8ae33fead3fa-attachment.txt",
      "type" : "text/plain",
      "size" : 980,
      "uid" : "e2250c715935cc08"
    }, {
      "title" : "实际code",
      "source" : "46d77054-d075-4fbf-a05d-6c96ecd0d2f8-attachment.txt",
      "type" : "text/plain",
      "size" : 3,
      "uid" : "831d89a3988b3863"
    }, {
      "title" : "实际data",
      "source" : "d786c4a6-9de8-4509-b297-a2b35b15f85b-attachment.txt",
      "type" : "text/plain",
      "size" : 980,
      "uid" : "79e593901f3069d8"
    } ],
    "steps" : [ ]
  } ],
  "attachments" : [ {
    "title" : "Captured log call",
    "source" : "efe10618-77b2-4ba3-8c77-c4e0021f77b3-attachment.txt",
    "type" : "text/plain",
    "size" : 3106,
    "uid" : "eb74c63ef92c3012"
  } ],
  "issues" : [ ],
  "labels" : [ {
    "name" : "story",
    "value" : "login"
  }, {
    "name" : "feature",
    "value" : "login"
  }, {
    "name" : "suite-name",
    "value" : "test_a_login"
  }, {
    "name" : "thread",
    "value" : "43007-MainThread"
  }, {
    "name" : "framework",
    "value" : "pytest"
  }, {
    "name" : "suite-title",
    "value" : null
  }, {
    "name" : "severity",
    "value" : "normal"
  }, {
    "name" : "host",
    "value" : "xiaoxideMacBook-Pro.local"
  }, {
    "name" : "language",
    "value" : "cpython3"
  } ],
  "parameters" : [ ]
}