{
  "uid" : "998a3402a076faf",
  "name" : "TestLogin.test_login[password_none]",
  "title" : "Test login [password_none]",
  "time" : {
    "start" : 1559723035124,
    "stop" : 1559723035561,
    "duration" : 437
  },
  "summary" : {
    "attachments" : 9,
    "steps" : 2
  },
  "failure" : null,
  "description" : {
    "value" : "\n        登录用例\n        :param case_data:\n        :return:\n        ",
    "type" : "TEXT"
  },
  "severity" : "NORMAL",
  "status" : "PASSED",
  "testId" : null,
  "suite" : {
    "uid" : "5d0930ef26b05c2f",
    "name" : "test_login",
    "title" : "Test login"
  },
  "steps" : [ {
    "name" : "POST请求接口",
    "title" : "POST请求接口",
    "time" : {
      "start" : 1559723035128,
      "stop" : 1559723035128,
      "duration" : 0
    },
    "summary" : {
      "attachments" : 4,
      "steps" : 0
    },
    "status" : "PASSED",
    "attachments" : [ {
      "title" : "请求接口：",
      "source" : "cc5eea06-1b98-4399-8379-19eae885d5e1-attachment.txt",
      "type" : "text/plain",
      "size" : 14,
      "uid" : "f40950f29bd739f3"
    }, {
      "title" : "请求地址",
      "source" : "f3ae23c6-f248-4671-8e62-be867de4ba84-attachment.txt",
      "type" : "text/plain",
      "size" : 46,
      "uid" : "6b9f86bc7187fd6"
    }, {
      "title" : "请求头",
      "source" : "e7969c56-f982-4e30-9ed2-fb4d44a60939-attachment.txt",
      "type" : "text/plain",
      "size" : 38,
      "uid" : "3ecca93ae1af56c6"
    }, {
      "title" : "请求参数",
      "source" : "7140fe5f-770e-4b04-b9fb-89c064297318-attachment.txt",
      "type" : "text/plain",
      "size" : 63,
      "uid" : "7f2a5c0ae6a4080a"
    } ],
    "steps" : [ ]
  }, {
    "name" : "JSON格式校验",
    "title" : "JSON格式校验",
    "time" : {
      "start" : 1559723035560,
      "stop" : 1559723035560,
      "duration" : 0
    },
    "summary" : {
      "attachments" : 4,
      "steps" : 0
    },
    "status" : "PASSED",
    "attachments" : [ {
      "title" : "期望code",
      "source" : "52ee9b12-444e-477f-8275-47265e3849ba-attachment.txt",
      "type" : "text/plain",
      "size" : 3,
      "uid" : "c87e8aa46f30739"
    }, {
      "title" : "期望data",
      "source" : "617096b6-5656-4100-8948-b4ea9c73af0b-attachment.txt",
      "type" : "text/plain",
      "size" : 53,
      "uid" : "4868d033391aee74"
    }, {
      "title" : "实际code",
      "source" : "7f35172e-feb4-4046-a2a7-a1f0f54ac006-attachment.txt",
      "type" : "text/plain",
      "size" : 3,
      "uid" : "fa10cc351e4c83ed"
    }, {
      "title" : "实际data",
      "source" : "434c203c-8f59-4938-ae8b-b05bcd08ac80-attachment.txt",
      "type" : "text/plain",
      "size" : 53,
      "uid" : "ee2ba527d667abe7"
    } ],
    "steps" : [ ]
  } ],
  "attachments" : [ {
    "title" : "Captured log call",
    "source" : "815ef6a2-ba02-4b09-9204-a9cb2ad380ea-attachment.txt",
    "type" : "text/plain",
    "size" : 1483,
    "uid" : "dd5cd0aaeff54a84"
  } ],
  "issues" : [ ],
  "labels" : [ {
    "name" : "story",
    "value" : "login"
  }, {
    "name" : "feature",
    "value" : "login"
  }, {
    "name" : "suite-name",
    "value" : "test_login"
  }, {
    "name" : "framework",
    "value" : "pytest"
  }, {
    "name" : "suite-title",
    "value" : null
  }, {
    "name" : "severity",
    "value" : "normal"
  }, {
    "name" : "host",
    "value" : "xiaoxideMacBook-Pro.local"
  }, {
    "name" : "thread",
    "value" : "30434-MainThread"
  }, {
    "name" : "language",
    "value" : "cpython3"
  } ],
  "parameters" : [ ]
}