{
  "uid" : "c15ebc1a747e76b5",
  "name" : "TestLogin.test_login[case_data1]",
  "title" : "Test login [case_data1]",
  "time" : {
    "start" : 1559615558053,
    "stop" : 1559615558510,
    "duration" : 457
  },
  "summary" : {
    "attachments" : 8,
    "steps" : 3
  },
  "failure" : null,
  "description" : {
    "value" : "password错误",
    "type" : "TEXT"
  },
  "severity" : "NORMAL",
  "status" : "PASSED",
  "testId" : null,
  "suite" : {
    "uid" : "d52eca209eaac701",
    "name" : "test_login",
    "title" : "Test login"
  },
  "steps" : [ {
    "name" : "POST请求接口",
    "title" : "POST请求接口",
    "time" : {
      "start" : 1559615558060,
      "stop" : 1559615558061,
      "duration" : 1
    },
    "summary" : {
      "attachments" : 4,
      "steps" : 0
    },
    "status" : "PASSED",
    "attachments" : [ {
      "title" : "请求接口：",
      "source" : "afae3083-8f86-4cd4-9aad-530ca19e462e-attachment.txt",
      "type" : "text/plain",
      "size" : 14,
      "uid" : "8662abbb982ad995"
    }, {
      "title" : "请求地址",
      "source" : "0984e24c-ee3b-47ae-894c-d0c452c9b5ea-attachment.txt",
      "type" : "text/plain",
      "size" : 46,
      "uid" : "73fda43cd0e2f21e"
    }, {
      "title" : "请求头",
      "source" : "f7c32b57-9847-42dd-a65f-74000a42b4b5-attachment.txt",
      "type" : "text/plain",
      "size" : 38,
      "uid" : "3de1bc1c2865109c"
    }, {
      "title" : "请求参数",
      "source" : "cebb06d9-3a64-437d-bfcd-6d00ecc04355-attachment.txt",
      "type" : "text/plain",
      "size" : 63,
      "uid" : "f9465e6db60bfa73"
    } ],
    "steps" : [ ]
  }, {
    "name" : "校验测试结果",
    "title" : "校验测试结果",
    "time" : {
      "start" : 1559615558509,
      "stop" : 1559615558509,
      "duration" : 0
    },
    "summary" : {
      "attachments" : 0,
      "steps" : 0
    },
    "status" : "PASSED",
    "attachments" : [ ],
    "steps" : [ ]
  }, {
    "name" : "完全校验",
    "title" : "完全校验",
    "time" : {
      "start" : 1559615558509,
      "stop" : 1559615558510,
      "duration" : 1
    },
    "summary" : {
      "attachments" : 4,
      "steps" : 0
    },
    "status" : "PASSED",
    "attachments" : [ {
      "title" : "期望code",
      "source" : "0369d361-7f6f-4b99-88d8-4569b6ffc8d7-attachment.txt",
      "type" : "text/plain",
      "size" : 3,
      "uid" : "21e01f0978daeaae"
    }, {
      "title" : "期望data",
      "source" : "260d9d95-1ef8-4bb3-b5c3-52f33f69bef0-attachment.txt",
      "type" : "text/plain",
      "size" : 60,
      "uid" : "42e427e38b267f83"
    }, {
      "title" : "实际code",
      "source" : "d65b4f90-2826-4c4f-ac07-d54f43eff067-attachment.txt",
      "type" : "text/plain",
      "size" : 3,
      "uid" : "d2d78b4357c76a27"
    }, {
      "title" : "实际data",
      "source" : "5dbac82f-884e-4645-8df7-e17e87fc896b-attachment.txt",
      "type" : "text/plain",
      "size" : 60,
      "uid" : "7129fc6894e27e7d"
    } ],
    "steps" : [ ]
  } ],
  "attachments" : [ ],
  "issues" : [ ],
  "labels" : [ {
    "name" : "thread",
    "value" : "24600-MainThread"
  }, {
    "name" : "feature",
    "value" : "用户登录场景"
  }, {
    "name" : "suite-name",
    "value" : "test_login"
  }, {
    "name" : "story",
    "value" : "登录"
  }, {
    "name" : "framework",
    "value" : "pytest"
  }, {
    "name" : "suite-title",
    "value" : null
  }, {
    "name" : "severity",
    "value" : "normal"
  }, {
    "name" : "host",
    "value" : "xiaoxideMacBook-Pro.local"
  }, {
    "name" : "language",
    "value" : "cpython3"
  } ],
  "parameters" : [ ]
}